README
setup.py
btn/__init__.py
btn/scrape.py
btn.egg-info/PKG-INFO
btn.egg-info/SOURCES.txt
btn.egg-info/dependency_links.txt
btn.egg-info/entry_points.txt
btn.egg-info/requires.txt
btn.egg-info/top_level.txt
btn/cli/__init__.py
btn/cli/scrape.py