Metadata-Version: 1.1
Name: btn
Version: 1.0.1
Summary: API and local cache for broadcasthe.net
Home-page: http://github.com/AllSeeingEyeTolledEweSew/btn
Author: AllSeeingEyeTolledEweSew
Author-email: allseeingeyetolledewesew@protonmail.com
License: Unlicense
Platform: UNKNOWN
Classifier: Development Status :: 5 - Production/Stable
Classifier: Intended Audience :: Developers
Classifier: License :: Public Domain
Classifier: Programming Language :: Python
Classifier: Topic :: Communications :: File Sharing
Classifier: Topic :: Database
Classifier: Topic :: Software Development :: Libraries :: Python Modules
Classifier: Topic :: System :: Networking
Classifier: Operating System :: OS Independent
Classifier: License :: Public Domain
